kronecker/__init__.py
kronecker/api.py
kronecker/core.py
kronecker/primitives.py
kronecker/backends/__init__.py
kronecker/backends/base.py
kronecker/backends/numpy.py
kronecker/backends/scipy_sparse.py
kronecker-0.0.2.dist-info/LICENSE
kronecker-0.0.2.dist-info/METADATA
kronecker-0.0.2.dist-info/WHEEL
kronecker-0.0.2.dist-info/top_level.txt
kronecker-0.0.2.dist-info/RECORD
