Metadata-Version: 2.1
Name: kronecker
Version: 0.0.2
Summary: Create boolean tensors / sparse matrices from index expressions
Home-page: https://github.com/PaulKlinger/kronecker
Author: Paul Klinger
Author-email: klinger.paul@gmail.com
License: UNKNOWN
Project-URL: Bug Tracker, https://github.com/PaulKlinger/kronecker/issues
Platform: UNKNOWN
Classifier: Programming Language :: Python :: 3
Classifier: License :: OSI Approved :: MIT License
Classifier: Operating System :: OS Independent
Requires-Python: >=3.8
License-File: LICENSE
Requires-Dist: numpy (>=1.18.0)
Requires-Dist: scipy (>=1.4.0)
